cq23/__init__.py
cq23/admin/__init__.py
cq23/admin/aws.py
cq23/admin/builder.py
cq23/admin/worker.py
cq23/build_image/__init__.py
cq23/build_image/command.py
cq23/build_image/docker_tools.py
cq23/check/__init__.py
cq23/check/command.py
cq23/cleanup/__init__.py
cq23/cleanup/command.py
cq23/client_logs/__init__.py
cq23/client_logs/command.py
cq23/main/__init__.py
cq23/main/command.py
cq23/main/utils.py
cq23/new_client/__init__.py
cq23/new_client/command.py
cq23/replay/__init__.py
cq23/replay/command.py
cq23/run_game/__init__.py
cq23/run_game/command.py
cq23/run_game/docker_tools.py
cq23/run_game/gcs.py
cq23/web_server/__init__.py
cq23/web_server/flask_api.py
cq23/web_server/files/loading_screen.html
cq23/zip/__init__.py
cq23/zip/command.py
cq23-2.6.1.dist-info/METADATA
cq23-2.6.1.dist-info/WHEEL
cq23-2.6.1.dist-info/entry_points.txt
cq23-2.6.1.dist-info/top_level.txt
cq23-2.6.1.dist-info/RECORD
