Metadata-Version: 2.1
Name: cq23
Version: 2.6.1
Summary: CLI Tools for CodeQuest 23
Home-page: https://github.com/CALED-Team/cq23-cli-utilities
Author: CodeQuest
Author-email: info@codequest.club
Project-URL: Bug Tracker, https://github.com/CALED-Team/cq23-cli-utilities/-/issues
Project-URL: repository, https://github.com/CALED-Team/cq23-cli-utilities
Classifier: Programming Language :: Python :: 3
Classifier: License :: OSI Approved :: MIT License
Classifier: Operating System :: OS Independent
Requires-Python: >=3.6
Requires-Dist: docker (>=6.0.1)
Requires-Dist: boto3 (>=1.26.143)
Requires-Dist: colorama (>=0.4.6)
Requires-Dist: flask (>=2.2.5)
Requires-Dist: flask-cors (>=3.0.10)
Requires-Dist: requests (>=2.31.0)
